oasist/__init__.py
oasist/oasist.py
oasist-1.1.0.dist-info/licenses/LICENSE
oasist-1.1.0.dist-info/METADATA
oasist-1.1.0.dist-info/WHEEL
oasist-1.1.0.dist-info/entry_points.txt
oasist-1.1.0.dist-info/top_level.txt
oasist-1.1.0.dist-info/RECORD
