Metadata-Version: 2.4
Name: oasist
Version: 1.1.0
Summary: OASist Client Generator: generate Python clients from OpenAPI schemas with auto-formatting, custom headers and environment variables
Author-email: AH Esmaeili <ah.esmaeili.79@gmail.com>
License-Expression: MIT
Project-URL: Repository, https://github.com/AhEsmaeili79/oasist
Keywords: openapi,client,generator,oas,oasist,black,formatting
Classifier: Development Status :: 5 - Production/Stable
Classifier: Intended Audience :: Developers
Classifier: Programming Language :: Python :: 3
Classifier: Programming Language :: Python :: 3.10
Classifier: Programming Language :: Python :: 3.11
Classifier: Programming Language :: Python :: 3.12
Classifier: Programming Language :: Python :: 3.13
Classifier: Operating System :: OS Independent
Classifier: Environment :: Console
Classifier: Topic :: Software Development :: Code Generators
Requires-Python: >=3.8
License-File: LICENSE
Requires-Dist: openapi-python-client<1.0.0,>=0.26.1
Requires-Dist: requests>=2.31.0
Requires-Dist: pyyaml>=6.0.1
Requires-Dist: rich>=13.7.0
Requires-Dist: python-dotenv>=1.0.1
Provides-Extra: formatting
Requires-Dist: black>=23.0.0; extra == "formatting"
Dynamic: license-file
